NosqlShujukuRumenjiaochengCYuyanBianchengWangFix1/README.md
NosqlShujukuRumenjiaochengCYuyanBianchengWangFix1/__init__.py
NosqlShujukuRumenjiaochengCYuyanBianchengWangFix1/__main__.py
NosqlShujukuRumenjiaochengCYuyanBianchengWangFix1/file.epub
NosqlShujukuRumenjiaochengCYuyanBianchengWangFix1/index.html
NosqlShujukuRumenjiaochengCYuyanBianchengWangFix1/css/__init__.py
NosqlShujukuRumenjiaochengCYuyanBianchengWangFix1/css/annotations.css
NosqlShujukuRumenjiaochengCYuyanBianchengWangFix1/css/main.css
NosqlShujukuRumenjiaochengCYuyanBianchengWangFix1/css/normalize.css
NosqlShujukuRumenjiaochengCYuyanBianchengWangFix1/css/popup.css
NosqlShujukuRumenjiaochengCYuyanBianchengWangFix1/font/__init__.py
NosqlShujukuRumenjiaochengCYuyanBianchengWangFix1/font/fontello.eot
NosqlShujukuRumenjiaochengCYuyanBianchengWangFix1/font/fontello.svg
NosqlShujukuRumenjiaochengCYuyanBianchengWangFix1/font/fontello.ttf
NosqlShujukuRumenjiaochengCYuyanBianchengWangFix1/font/fontello.woff
NosqlShujukuRumenjiaochengCYuyanBianchengWangFix1/img/__init__.py
NosqlShujukuRumenjiaochengCYuyanBianchengWangFix1/img/annotator-glyph-sprite.png
NosqlShujukuRumenjiaochengCYuyanBianchengWangFix1/img/annotator-icon-sprite.png
NosqlShujukuRumenjiaochengCYuyanBianchengWangFix1/img/apple-touch-icon.png
NosqlShujukuRumenjiaochengCYuyanBianchengWangFix1/img/cancelfullscreen.png
NosqlShujukuRumenjiaochengCYuyanBianchengWangFix1/img/close.png
NosqlShujukuRumenjiaochengCYuyanBianchengWangFix1/img/fullscreen.png
NosqlShujukuRumenjiaochengCYuyanBianchengWangFix1/img/loader.gif
NosqlShujukuRumenjiaochengCYuyanBianchengWangFix1/img/menu-icon.png
NosqlShujukuRumenjiaochengCYuyanBianchengWangFix1/img/save.png
NosqlShujukuRumenjiaochengCYuyanBianchengWangFix1/img/saved.png
NosqlShujukuRumenjiaochengCYuyanBianchengWangFix1/img/settings-s.png
NosqlShujukuRumenjiaochengCYuyanBianchengWangFix1/img/settings.png
NosqlShujukuRumenjiaochengCYuyanBianchengWangFix1/img/star.png
nosql_shujuku_rumenjiaocheng_c_yuyan_biancheng_wang_fix1-2025.3.24.0.dist-info/METADATA
nosql_shujuku_rumenjiaocheng_c_yuyan_biancheng_wang_fix1-2025.3.24.0.dist-info/WHEEL
nosql_shujuku_rumenjiaocheng_c_yuyan_biancheng_wang_fix1-2025.3.24.0.dist-info/entry_points.txt
nosql_shujuku_rumenjiaocheng_c_yuyan_biancheng_wang_fix1-2025.3.24.0.dist-info/top_level.txt
nosql_shujuku_rumenjiaocheng_c_yuyan_biancheng_wang_fix1-2025.3.24.0.dist-info/RECORD
